{"featureCount":7,"formatVersion":1,"histograms":{"meta":[{"arrayParams":{"chunkSize":10000,"length":2,"urlTemplate":"hist-50000-{Chunk}.json"},"basesPerBin":"50000"}],"stats":[{"basesPerBin":"50000","max":6,"mean":3.5}]},"intervals":{"classes":[{"attributes":["Start","End","Strand","Id","Name","Seq_id","Source","Subfeatures","Type"],"isArrayAttr":{"Subfeatures":1}},{"attributes":["Start","End","Strand","Id","Seq_id","Source","Type"],"isArrayAttr":{}},{"attributes":["Start","End","Strand","Id","Phase","Seq_id","Source","Type"],"isArrayAttr":{}},{"attributes":["Start","End","Chunk"],"isArrayAttr":{"Sublist":1}}],"count":7,"lazyClass":3,"maxEnd":81491,"minStart":12323,"nclist":[[0,12323,12830,1,"BnaS00913g010.1DH","BnaS00913g010.1DH","Scaffold00913","AAFC_GIFS",[[0,12323,12830,1,"BnaS00913g010.1DH.1","BnaS00913g010.1DH.1","Scaffold00913","AAFC_GIFS",[[1,12323,12830,1,"BnaS00913g010.1DH.1.exon1","Scaffold00913","AAFC_GIFS","exon"],[2,12323,12830,1,"BnaS00913g010.1DH.1.cds1",0,"Scaffold00913","AAFC_GIFS","CDS"]],"mRNA"]],"gene"],[0,13117,14154,1,"BnaS00913g020.1DH","BnaS00913g020.1DH","Scaffold00913","AAFC_GIFS",[[0,13117,14154,1,"BnaS00913g020.1DH.1","BnaS00913g020.1DH.1","Scaffold00913","AAFC_GIFS",[[1,13117,13554,1,"BnaS00913g020.1DH.1.exon1","Scaffold00913","AAFC_GIFS","exon"],[1,13703,14154,1,"BnaS00913g020.1DH.1.exon2","Scaffold00913","AAFC_GIFS","exon"],[2,13117,13554,1,"BnaS00913g020.1DH.1.cds1",0,"Scaffold00913","AAFC_GIFS","CDS"],[2,13703,14154,1,"BnaS00913g020.1DH.1.cds2",1,"Scaffold00913","AAFC_GIFS","CDS"]],"mRNA"]],"gene"],[0,19190,19619,-1,"BnaS00913g030.1DH","BnaS00913g030.1DH","Scaffold00913","AAFC_GIFS",[[0,19190,19619,-1,"BnaS00913g030.1DH.1","BnaS00913g030.1DH.1","Scaffold00913","AAFC_GIFS",[[1,19190,19619,-1,"BnaS00913g030.1DH.1.exon1","Scaffold00913","AAFC_GIFS","exon"],[2,19190,19619,-1,"BnaS00913g030.1DH.1.cds1",0,"Scaffold00913","AAFC_GIFS","CDS"]],"mRNA"]],"gene"],[0,19679,19910,-1,"BnaS00913g040.1DH","BnaS00913g040.1DH","Scaffold00913","AAFC_GIFS",[[0,19679,19910,-1,"BnaS00913g040.1DH.1","BnaS00913g040.1DH.1","Scaffold00913","AAFC_GIFS",[[1,19679,19910,-1,"BnaS00913g040.1DH.1.exon1","Scaffold00913","AAFC_GIFS","exon"],[2,19679,19910,-1,"BnaS00913g040.1DH.1.cds1",0,"Scaffold00913","AAFC_GIFS","CDS"]],"mRNA"]],"gene"],[0,26471,27227,-1,"BnaS00913g050.1DH","BnaS00913g050.1DH","Scaffold00913","AAFC_GIFS",[[0,26471,27227,-1,"BnaS00913g050.1DH.1","BnaS00913g050.1DH.1","Scaffold00913","AAFC_GIFS",[[1,26471,27227,-1,"BnaS00913g050.1DH.1.exon1","Scaffold00913","AAFC_GIFS","exon"],[2,26471,27227,-1,"BnaS00913g050.1DH.1.cds1",0,"Scaffold00913","AAFC_GIFS","CDS"]],"mRNA"]],"gene"],[0,27892,28525,-1,"BnaS00913g060.1DH","BnaS00913g060.1DH","Scaffold00913","AAFC_GIFS",[[0,27892,28525,-1,"BnaS00913g060.1DH.1","BnaS00913g060.1DH.1","Scaffold00913","AAFC_GIFS",[[1,27892,28525,-1,"BnaS00913g060.1DH.1.exon1","Scaffold00913","AAFC_GIFS","exon"],[2,27892,28525,-1,"BnaS00913g060.1DH.1.cds1",0,"Scaffold00913","AAFC_GIFS","CDS"]],"mRNA"]],"gene"],[0,81281,81491,1,"BnaS00913g070.1DH","BnaS00913g070.1DH","Scaffold00913","AAFC_GIFS",[[0,81281,81491,1,"BnaS00913g070.1DH.1","BnaS00913g070.1DH.1","Scaffold00913","AAFC_GIFS",[[1,81281,81491,1,"BnaS00913g070.1DH.1.exon1","Scaffold00913","AAFC_GIFS","exon"],[2,81281,81491,1,"BnaS00913g070.1DH.1.cds1",0,"Scaffold00913","AAFC_GIFS","CDS"]],"mRNA"]],"gene"]],"urlTemplate":"lf-{Chunk}.json"}}