{"featureCount":2,"formatVersion":1,"histograms":{"meta":[{"arrayParams":{"chunkSize":10000,"length":1,"urlTemplate":"hist-5000-{Chunk}.json"},"basesPerBin":"5000"}],"stats":[{"basesPerBin":"5000","max":2,"mean":2}]},"intervals":{"classes":[{"attributes":["Start","End","Strand","Id","Name","Seq_id","Source","Subfeatures","Type"],"isArrayAttr":{"Subfeatures":1}},{"attributes":["Start","End","Strand","Id","Seq_id","Source","Type"],"isArrayAttr":{}},{"attributes":["Start","End","Strand","Id","Phase","Seq_id","Source","Type"],"isArrayAttr":{}},{"attributes":["Start","End","Chunk"],"isArrayAttr":{"Sublist":1}}],"count":2,"lazyClass":3,"maxEnd":2813,"minStart":439,"nclist":[[0,439,861,1,"BnaS03515g010.1DH","BnaS03515g010.1DH","Scaffold03515","AAFC_GIFS",[[0,439,861,1,"BnaS03515g010.1DH.1","BnaS03515g010.1DH.1","Scaffold03515","AAFC_GIFS",[[1,439,541,1,"BnaS03515g010.1DH.1.exon1","Scaffold03515","AAFC_GIFS","exon"],[1,714,779,1,"BnaS03515g010.1DH.1.exon2","Scaffold03515","AAFC_GIFS","exon"],[1,854,861,1,"BnaS03515g010.1DH.1.exon3","Scaffold03515","AAFC_GIFS","exon"],[2,439,541,1,"BnaS03515g010.1DH.1.cds1",0,"Scaffold03515","AAFC_GIFS","CDS"],[2,714,779,1,"BnaS03515g010.1DH.1.cds2",0,"Scaffold03515","AAFC_GIFS","CDS"],[2,854,861,1,"BnaS03515g010.1DH.1.cds3",1,"Scaffold03515","AAFC_GIFS","CDS"]],"mRNA"]],"gene"],[0,883,2813,1,"BnaS03515g020.1DH","BnaS03515g020.1DH","Scaffold03515","AAFC_GIFS",[[0,883,2813,1,"BnaS03515g020.1DH.1","BnaS03515g020.1DH.1","Scaffold03515","AAFC_GIFS",[[1,883,888,1,"BnaS03515g020.1DH.1.exon1","Scaffold03515","AAFC_GIFS","exon"],[1,961,1006,1,"BnaS03515g020.1DH.1.exon2","Scaffold03515","AAFC_GIFS","exon"],[1,1080,1435,1,"BnaS03515g020.1DH.1.exon3","Scaffold03515","AAFC_GIFS","exon"],[1,1511,1703,1,"BnaS03515g020.1DH.1.exon4","Scaffold03515","AAFC_GIFS","exon"],[1,1774,2074,1,"BnaS03515g020.1DH.1.exon5","Scaffold03515","AAFC_GIFS","exon"],[1,2153,2813,1,"BnaS03515g020.1DH.1.exon6","Scaffold03515","AAFC_GIFS","exon"],[2,883,888,1,"BnaS03515g020.1DH.1.cds1",0,"Scaffold03515","AAFC_GIFS","CDS"],[2,961,1006,1,"BnaS03515g020.1DH.1.cds2",1,"Scaffold03515","AAFC_GIFS","CDS"],[2,1080,1435,1,"BnaS03515g020.1DH.1.cds3",1,"Scaffold03515","AAFC_GIFS","CDS"],[2,1511,1703,1,"BnaS03515g020.1DH.1.cds4",0,"Scaffold03515","AAFC_GIFS","CDS"],[2,1774,2074,1,"BnaS03515g020.1DH.1.cds5",0,"Scaffold03515","AAFC_GIFS","CDS"],[2,2153,2813,1,"BnaS03515g020.1DH.1.cds6",0,"Scaffold03515","AAFC_GIFS","CDS"]],"mRNA"]],"gene"]],"urlTemplate":"lf-{Chunk}.json"}}